minihtml/__init__.py
minihtml/_component.py
minihtml/_core.py
minihtml/_template.py
minihtml/_template_context.py
minihtml/py.typed
minihtml/tags.py
minihtml-0.2.3.dist-info/METADATA
minihtml-0.2.3.dist-info/WHEEL
minihtml-0.2.3.dist-info/licenses/LICENSE
minihtml-0.2.3.dist-info/RECORD
