Metadata-Version: 2.4
Name: minihtml
Version: 0.2.3
Summary: Simple HTML Generation
Project-URL: Homepage, https://github.com/trendels/minihtml
Project-URL: Source, https://github.com/trendels/minihtml
Project-URL: Changelog, https://github.com/trendels/minihtml/blob/main/Changelog.md
Author-email: Stanis Trendelenburg <stanis.trendelenburg@gmail.com>
License-Expression: MIT
License-File: LICENSE
Requires-Python: >=3.10
Requires-Dist: typing-extensions>=4.12.2; python_full_version < '3.11'
